gir-0.0.0.dist-info/DESCRIPTION.rst
gir-0.0.0.dist-info/METADATA
gir-0.0.0.dist-info/WHEEL
gir-0.0.0.dist-info/top_level.txt
gir-0.0.0.dist-info/entry_points.txt
gir-0.0.0.dist-info/RECORD
gir-0.0.0.dist-info/metadata.json
gir-0.0.0.dist-info/zip-safe
gir/OutputBuffer.py
gir/ScrollWindow.py
gir/WindowWrapper.py
gir/__init__.py
gir/Color.py
