Metadata-Version: 2.0
Name: gir
Version: 0.0.0
Summary: UNKNOWN
Home-page: https://github.com/mrozekma/gir
Author: Michael Mrozek
Author-email: git@mrozekma.com
License: MIT
Platform: UNKNOWN
Classifier: Environment :: Console :: Curses
Classifier: Intended Audience :: Developers
Classifier: License :: OSI Approved :: MIT License
Classifier: Programming Language :: Python :: 2.7
Classifier: Topic :: Software Development :: Version Control
Requires-Dist: GitPython
